rtl/control_fsm.v
module control_fsm (
    input  wire       clk,
    input  wire       reset,
    input  wire       halt_req,

    output reg  [2:0] state,

    output wire       fetch_state,
    output wire       decode_state,
    output wire       execute_state,
    output wire       writeback_state,
    output wire       halted
);

    reg [2:0] next_state;


    localparam FETCH     = 3'd0;
    localparam DECODE    = 3'd1;
    localparam EXECUTE   = 3'd2;
    localparam WRITEBACK = 3'd3;
    localparam HALT      = 3'd4;


    // State register
    always @(posedge clk) begin

        if (reset) begin
            state <= FETCH;
        end

        else begin
            state <= next_state;
        end

    end


    // Next-state logic
    always @(*) begin

        // Default: remain in current state
        next_state = state;

        case (state)

            FETCH: begin
                next_state = DECODE;
            end


            DECODE: begin

                if (halt_req) begin
                    next_state = HALT;
                end

                else begin
                    next_state = EXECUTE;
                end

            end


            EXECUTE: begin
                next_state = WRITEBACK;
            end


            WRITEBACK: begin
                next_state = FETCH;
            end


            HALT: begin
                next_state = HALT;
            end


            default: begin
                next_state = FETCH;
            end

        endcase

    end


    assign fetch_state     = (state == FETCH);
    assign decode_state    = (state == DECODE);
    assign execute_state   = (state == EXECUTE);
    assign writeback_state = (state == WRITEBACK);
    assign halted          = (state == HALT);


endmodule

tb/control_fsm_tb.v
`timescale 1ns/1ps

module control_fsm_tb;

    reg clk;
    reg reset;
    reg halt_req;

    wire [2:0] state;

    wire fetch_state;
    wire decode_state;
    wire execute_state;
    wire writeback_state;
    wire halted;


    control_fsm dut (
        .clk(clk),
        .reset(reset),
        .halt_req(halt_req),

        .state(state),

        .fetch_state(fetch_state),
        .decode_state(decode_state),
        .execute_state(execute_state),
        .writeback_state(writeback_state),
        .halted(halted)
    );


    // Clock generator
    initial begin
        clk = 0;
        forever #5 clk = ~clk;
    end


    initial begin

        $dumpfile("sim/control_fsm.vcd");
        $dumpvars(0, control_fsm_tb);

        $display(
            "TIME CLK RESET HALT_REQ | STATE | F D E W H"
        );

        $monitor(
            "%4t  %b    %b      %b     |  %b  | %b %b %b %b %b",
            $time,
            clk,
            reset,
            halt_req,
            state,
            fetch_state,
            decode_state,
            execute_state,
            writeback_state,
            halted
        );


        // Start in reset
        reset    = 1;
        halt_req = 0;

        #10;


        // Release reset
        reset = 0;

        // Allow one full instruction cycle
        #40;


        // Request HALT
        halt_req = 1;

        #20;


        // Remove request - CPU should remain halted
        halt_req = 0;

        #20;


        // Reset should restart CPU
        reset = 1;

        #10;


        reset = 0;

        #20;


        $finish;

    end

endmodule

sim/control_fsm.vcd
$date
	Thu Aug 27 13:17:38 2026
$end
$version
	Icarus Verilog
$end
$timescale
	1ps
$end
$scope module control_fsm_tb $end
$var wire 1 ! writeback_state $end
$var wire 3 " state [2:0] $end
$var wire 1 # halted $end
$var wire 1 $ fetch_state $end
$var wire 1 % execute_state $end
$var wire 1 & decode_state $end
$var reg 1 ' clk $end
$var reg 1 ( halt_req $end
$var reg 1 ) reset $end
$scope module dut $end
$var wire 1 ' clk $end
$var wire 1 ( halt_req $end
$var wire 1 ) reset $end
$var wire 1 ! writeback_state $end
$var wire 1 # halted $end
$var wire 1 $ fetch_state $end
$var wire 1 % execute_state $end
$var wire 1 & decode_state $end
$var parameter 3 * DECODE $end
$var parameter 3 + EXECUTE $end
$var parameter 3 , FETCH $end
$var parameter 3 - HALT $end
$var parameter 3 . WRITEBACK $end
$var reg 3 / next_state [2:0] $end
$var reg 3 0 state [2:0] $end
$upscope $end
$upscope $end
$enddefinitions $end
$comment Show the parameter values. $end
$dumpall
b11 .
b100 -
b0 ,
b10 +
b1 *
$end
#0
$dumpvars
bx 0
b0 /
1)
0(
0'
x&
x%
x$
x#
bx "
x!
$end
#5000
b1 /
1$
0&
0%
0!
0#
b0 "
b0 0
1'
#10000
0'
0)
#15000
b10 /
0$
1&
b1 "
b1 0
1'
#20000
0'
#25000
b11 /
0&
1%
b10 "
b10 0
1'
#30000
0'
#35000
b0 /
0%
1!
b11 "
b11 0
1'
#40000
0'
#45000
b1 /
1$
0!
b0 "
b0 0
1'
#50000
b1 /
0'
1(
#55000
b100 /
0$
1&
b1 "
b1 0
1'
#60000
0'
#65000
0&
1#
b100 "
b100 0
1'
#70000
0'
0(
#75000
1'
#80000
0'
#85000
1'
#90000
0'
1)
#95000
b1 /
1$
0#
b0 "
b0 0
1'
#100000
0'
0)
#105000
b10 /
0$
1&
b1 "
b1 0
1'
#110000
0'
#115000
b11 /
0&
1%
b10 "
b10 0
1'
