rtl/control_unit.v
module control_unit (
    input  wire [3:0] opcode,

    output reg  [2:0] alu_op,
    output reg  [1:0] wb_sel,

    output reg        reg_write_req,
    output reg        flag_write_req,

    output reg        mem_read_req,
    output reg        mem_write_req,

    output reg        jump,
    output reg        jump_zero,

    output reg        halt
);

    always @(*) begin

        // Default values
        alu_op         = 3'b000;
        wb_sel         = 2'b00;

        reg_write_req  = 1'b0;
        flag_write_req = 1'b0;

        mem_read_req   = 1'b0;
        mem_write_req  = 1'b0;

        jump            = 1'b0;
        jump_zero       = 1'b0;

        halt            = 1'b0;


        case (opcode)

            // NOP
            4'b0000: begin
            end


            // LDI Rd, immediate
            4'b0001: begin
                reg_write_req = 1'b1;
                wb_sel        = 2'b01;
            end


            // MOV Rd, Rs
            4'b0010: begin
                reg_write_req = 1'b1;
                wb_sel        = 2'b11;
            end


            // ADD Rd, Rs
            4'b0011: begin
                alu_op         = 3'b000;
                reg_write_req  = 1'b1;
                flag_write_req = 1'b1;
                wb_sel         = 2'b00;
            end


            // SUB Rd, Rs
            4'b0100: begin
                alu_op         = 3'b001;
                reg_write_req  = 1'b1;
                flag_write_req = 1'b1;
                wb_sel         = 2'b00;
            end


            // AND Rd, Rs
            4'b0101: begin
                alu_op         = 3'b010;
                reg_write_req  = 1'b1;
                flag_write_req = 1'b1;
                wb_sel         = 2'b00;
            end


            // OR Rd, Rs
            4'b0110: begin
                alu_op         = 3'b011;
                reg_write_req  = 1'b1;
                flag_write_req = 1'b1;
                wb_sel         = 2'b00;
            end


            // XOR Rd, Rs
            4'b0111: begin
                alu_op         = 3'b100;
                reg_write_req  = 1'b1;
                flag_write_req = 1'b1;
                wb_sel         = 2'b00;
            end


            // LOAD Rd, address
            4'b1000: begin
                reg_write_req = 1'b1;
                mem_read_req  = 1'b1;
                wb_sel        = 2'b10;
            end


            // STORE Rd, address
            4'b1001: begin
                mem_write_req = 1'b1;
            end


            // JMP address
            4'b1010: begin
                jump = 1'b1;
            end


            // JZ address
            4'b1011: begin
                jump_zero = 1'b1;
            end


            // CMP Rd, Rs
            4'b1100: begin
                alu_op         = 3'b001;
                flag_write_req = 1'b1;
            end


            // Reserved
            4'b1101: begin
            end


            // Reserved
            4'b1110: begin
            end


            // HALT
            4'b1111: begin
                halt = 1'b1;
            end


        endcase

    end

endmodule

tb/tb:control_unit_tb.v
`timescale 1ns/1ps

module control_unit_tb;

    reg [3:0] opcode;

    wire [2:0] alu_op;
    wire [1:0] wb_sel;

    wire reg_write_req;
    wire flag_write_req;

    wire mem_read_req;
    wire mem_write_req;

    wire jump;
    wire jump_zero;

    wire halt;


    control_unit dut (
        .opcode(opcode),

        .alu_op(alu_op),
        .wb_sel(wb_sel),

        .reg_write_req(reg_write_req),
        .flag_write_req(flag_write_req),

        .mem_read_req(mem_read_req),
        .mem_write_req(mem_write_req),

        .jump(jump),
        .jump_zero(jump_zero),

        .halt(halt)
    );


    initial begin

        $dumpfile("sim/control_unit.vcd");
        $dumpvars(0, control_unit_tb);

        $display(
            "OPCODE | ALU WB | RW FW MR MW | JMP JZ HALT"
        );

        $monitor(
            " %b   | %b  %b |  %b  %b  %b  %b |  %b   %b   %b",
            opcode,
            alu_op,
            wb_sel,
            reg_write_req,
            flag_write_req,
            mem_read_req,
            mem_write_req,
            jump,
            jump_zero,
            halt
        );


        // NOP
        opcode = 4'b0000;
        #10;

        // LDI
        opcode = 4'b0001;
        #10;

        // MOV
        opcode = 4'b0010;
        #10;

        // ADD
        opcode = 4'b0011;
        #10;

        // SUB
        opcode = 4'b0100;
        #10;

        // LOAD
        opcode = 4'b1000;
        #10;

        // STORE
        opcode = 4'b1001;
        #10;

        // JMP
        opcode = 4'b1010;
        #10;

        // JZ
        opcode = 4'b1011;
        #10;

        // CMP
        opcode = 4'b1100;
        #10;

        // HALT
        opcode = 4'b1111;
        #10;


        $finish;

    end

endmodule

sim/control_unit.vcd
$date
	Thu Aug 27 13:03:12 2026
$end
$version
	Icarus Verilog
$end
$timescale
	1ps
$end
$scope module control_unit_tb $end
$var wire 2 ! wb_sel [1:0] $end
$var wire 1 " reg_write_req $end
$var wire 1 # mem_write_req $end
$var wire 1 $ mem_read_req $end
$var wire 1 % jump_zero $end
$var wire 1 & jump $end
$var wire 1 ' halt $end
$var wire 1 ( flag_write_req $end
$var wire 3 ) alu_op [2:0] $end
$var reg 4 * opcode [3:0] $end
$scope module dut $end
$var wire 4 + opcode [3:0] $end
$var reg 3 , alu_op [2:0] $end
$var reg 1 ( flag_write_req $end
$var reg 1 ' halt $end
$var reg 1 & jump $end
$var reg 1 % jump_zero $end
$var reg 1 $ mem_read_req $end
$var reg 1 # mem_write_req $end
$var reg 1 " reg_write_req $end
$var reg 2 - wb_sel [1:0] $end
$upscope $end
$upscope $end
$enddefinitions $end
$comment Show the parameter values. $end
$dumpall
$end
#0
$dumpvars
b0 -
b0 ,
b0 +
b0 *
b0 )
0(
0'
0&
0%
0$
0#
0"
b0 !
$end
#10000
b1 !
b1 -
1"
b1 *
b1 +
#20000
1"
b11 !
b11 -
b10 *
b10 +
#30000
1(
1"
b0 !
b0 -
b11 *
b11 +
#40000
b1 )
b1 ,
1(
1"
b100 *
b100 +
#50000
b10 !
b10 -
1$
0(
1"
b0 )
b0 ,
b1000 *
b1000 +
#60000
1#
0$
0"
b0 !
b0 -
b1001 *
b1001 +
#70000
1&
0#
b1010 *
b1010 +
#80000
1%
0&
b1011 *
b1011 +
#90000
1(
b1 )
b1 ,
0%
b1100 *
b1100 +
#100000
1'
0(
b0 )
b0 ,
b1111 *
b1111 +
