rtl/data_memory.v
module data_memory (
    input  wire       clk,

    input  wire       mem_read,
    input  wire       mem_write,

    input  wire [7:0] address,
    input  wire [7:0] write_data,

    output wire [7:0] read_data
);

    reg [7:0] memory [0:255];

    integer i;


    // Initialise memory to zero for simulation
    initial begin
        for (i = 0; i < 256; i = i + 1) begin
            memory[i] = 8'b00000000;
        end
    end


    // Combinational read
    assign read_data =
        mem_read ? memory[address] : 8'b00000000;


    // Clocked write
    always @(posedge clk) begin

        if (mem_write) begin
            memory[address] <= write_data;
        end

    end

endmodule

rtl/status_register.v
module status_register (
    input  wire clk,
    input  wire reset,
    input  wire write_enable,

    input  wire zero_in,
    input  wire carry_in,

    output reg  zero_flag,
    output reg  carry_flag
);

    always @(posedge clk) begin

        if (reset) begin
            zero_flag  <= 1'b0;
            carry_flag <= 1'b0;
        end

        else if (write_enable) begin
            zero_flag  <= zero_in;
            carry_flag <= carry_in;
        end

    end

endmodule

rtl/alu.v
module alu (
    input  wire [7:0] a,
    input  wire [7:0] b,
    input  wire [2:0] op,
    output reg  [7:0] result,
    output reg        zero,
    output reg        carry
);

always @(*) begin

    carry = 1'b0;

    case (op)

        3'b000: begin
            {carry, result} = a + b;
        end

        3'b001: begin
            result = a - b;
        end

        3'b010: begin
            result = a & b;
        end

        3'b011: begin
            result = a | b;
        end

        3'b100: begin
            result = a ^ b;
        end

        default: begin
            result = 8'b00000000;
        end

    endcase

    zero = (result == 8'b00000000);

end

endmodule

rtl/register_file.v
module register_file (
    input  wire       clk,
    input  wire       reset,

    input  wire [2:0] read_addr1,
    input  wire [2:0] read_addr2,

    input  wire [2:0] write_addr,
    input  wire [7:0] write_data,
    input  wire       write_enable,

    output wire [7:0] read_data1,
    output wire [7:0] read_data2
);

    reg [7:0] registers [0:7];

    integer i;

    assign read_data1 = registers[read_addr1];
    assign read_data2 = registers[read_addr2];

    always @(posedge clk) begin

        if (reset) begin

            for (i = 0; i < 8; i = i + 1) begin
                registers[i] <= 8'b00000000;
            end

        end
        else if (write_enable) begin

            registers[write_addr] <= write_data;

        end

    end

endmodule

rtl/control_fsm.v
module control_fsm (
    input  wire       clk,
    input  wire       reset,
    input  wire       halt_req,

    output reg  [2:0] state,

    output wire       fetch_state,
    output wire       decode_state,
    output wire       execute_state,
    output wire       writeback_state,
    output wire       halted
);

    reg [2:0] next_state;


    localparam FETCH     = 3'd0;
    localparam DECODE    = 3'd1;
    localparam EXECUTE   = 3'd2;
    localparam WRITEBACK = 3'd3;
    localparam HALT      = 3'd4;


    // State register
    always @(posedge clk) begin

        if (reset) begin
            state <= FETCH;
        end

        else begin
            state <= next_state;
        end

    end


    // Next-state logic
    always @(*) begin

        // Default: remain in current state
        next_state = state;

        case (state)

            FETCH: begin
                next_state = DECODE;
            end


            DECODE: begin

                if (halt_req) begin
                    next_state = HALT;
                end

                else begin
                    next_state = EXECUTE;
                end

            end


            EXECUTE: begin
                next_state = WRITEBACK;
            end


            WRITEBACK: begin
                next_state = FETCH;
            end


            HALT: begin
                next_state = HALT;
            end


            default: begin
                next_state = FETCH;
            end

        endcase

    end


    assign fetch_state     = (state == FETCH);
    assign decode_state    = (state == DECODE);
    assign execute_state   = (state == EXECUTE);
    assign writeback_state = (state == WRITEBACK);
    assign halted          = (state == HALT);


endmodule

rtl/control_unit.v
module control_unit (
    input  wire [3:0] opcode,

    output reg  [2:0] alu_op,
    output reg  [1:0] wb_sel,

    output reg        reg_write_req,
    output reg        flag_write_req,

    output reg        mem_read_req,
    output reg        mem_write_req,

    output reg        jump,
    output reg        jump_zero,

    output reg        halt
);

    always @(*) begin

        // Default values
        alu_op         = 3'b000;
        wb_sel         = 2'b00;

        reg_write_req  = 1'b0;
        flag_write_req = 1'b0;

        mem_read_req   = 1'b0;
        mem_write_req  = 1'b0;

        jump            = 1'b0;
        jump_zero       = 1'b0;

        halt            = 1'b0;


        case (opcode)

            // NOP
            4'b0000: begin
            end


            // LDI Rd, immediate
            4'b0001: begin
                reg_write_req = 1'b1;
                wb_sel        = 2'b01;
            end


            // MOV Rd, Rs
            4'b0010: begin
                reg_write_req = 1'b1;
                wb_sel        = 2'b11;
            end


            // ADD Rd, Rs
            4'b0011: begin
                alu_op         = 3'b000;
                reg_write_req  = 1'b1;
                flag_write_req = 1'b1;
                wb_sel         = 2'b00;
            end


            // SUB Rd, Rs
            4'b0100: begin
                alu_op         = 3'b001;
                reg_write_req  = 1'b1;
                flag_write_req = 1'b1;
                wb_sel         = 2'b00;
            end


            // AND Rd, Rs
            4'b0101: begin
                alu_op         = 3'b010;
                reg_write_req  = 1'b1;
                flag_write_req = 1'b1;
                wb_sel         = 2'b00;
            end


            // OR Rd, Rs
            4'b0110: begin
                alu_op         = 3'b011;
                reg_write_req  = 1'b1;
                flag_write_req = 1'b1;
                wb_sel         = 2'b00;
            end


            // XOR Rd, Rs
            4'b0111: begin
                alu_op         = 3'b100;
                reg_write_req  = 1'b1;
                flag_write_req = 1'b1;
                wb_sel         = 2'b00;
            end


            // LOAD Rd, address
            4'b1000: begin
                reg_write_req = 1'b1;
                mem_read_req  = 1'b1;
                wb_sel        = 2'b10;
            end


            // STORE Rd, address
            4'b1001: begin
                mem_write_req = 1'b1;
            end


            // JMP address
            4'b1010: begin
                jump = 1'b1;
            end


            // JZ address
            4'b1011: begin
                jump_zero = 1'b1;
            end


            // CMP Rd, Rs
            4'b1100: begin
                alu_op         = 3'b001;
                flag_write_req = 1'b1;
            end


            // Reserved
            4'b1101: begin
            end


            // Reserved
            4'b1110: begin
            end


            // HALT
            4'b1111: begin
                halt = 1'b1;
            end


        endcase

    end

endmodule

rtl/instruction_decoder.v
module instruction_decoder (
    input  wire [15:0] instruction,

    output wire [3:0] opcode,
    output wire [2:0] rd,
    output wire [2:0] rs,
    output wire [7:0] immediate
);

    assign opcode    = instruction[15:12];
    assign rd        = instruction[11:9];
    assign rs        = instruction[8:6];
    assign immediate = instruction[7:0];

endmodule

rtl/instruction_register.v
module instruction_register (
    input  wire        clk,
    input  wire        reset,
    input  wire        load,

    input  wire [15:0] instruction_in,
    output reg  [15:0] instruction_out
);

    always @(posedge clk) begin

        if (reset) begin
            instruction_out <= 16'b0000000000000000;
        end

        else if (load) begin
            instruction_out <= instruction_in;
        end

    end

endmodule

rtl/instruction_memory.v
module instruction_memory #(
    parameter MEM_FILE = "programs/test_program.mem"
)(
    input  wire [7:0]  address,
    output wire [15:0] instruction
);

    reg [15:0] memory [0:255];

    integer i;

    initial begin

        // Fill unused instruction locations with NOP
        for (i = 0; i < 256; i = i + 1) begin
            memory[i] = 16'b0000000000000000;
        end

        // Load selected MiniRISC program
        $readmemb(MEM_FILE, memory);

    end

    assign instruction = memory[address];

endmodule

rtl/program_counter.v
module program_counter (
    input  wire       clk,
    input  wire       reset,
    input  wire       enable,
    input  wire       load,
    input  wire [7:0] next_pc,
    output reg  [7:0] pc
);

    always @(posedge clk) begin

        if (reset) begin
            pc <= 8'b00000000;
        end

        else if (enable) begin

            if (load) begin
                pc <= next_pc;
            end

            else begin
                pc <= pc + 8'd1;
            end

        end

    end

endmodule

rtl/minirisc_cpu.v
module minirisc_cpu #(
    parameter PROGRAM_FILE = "programs/test_program.mem"
)(
    input  wire        clk,
    input  wire        reset,

    // Debug outputs
    output wire [7:0]  pc_debug,
    output wire [15:0] instruction_debug,
    output wire [2:0]  state_debug,
    output wire        zero_debug,
    output wire        carry_debug,
    output wire        halted
);


    // ============================================================
    // PROGRAM COUNTER SIGNALS
    // ============================================================

    wire [7:0] pc;

    wire       pc_enable;
    wire       pc_load;
    wire [7:0] next_pc;


    // ============================================================
    // INSTRUCTION MEMORY / INSTRUCTION REGISTER
    // ============================================================

    wire [15:0] instruction_from_memory;
    wire [15:0] current_instruction;


    // ============================================================
    // INSTRUCTION DECODER SIGNALS
    // ============================================================

    wire [3:0] opcode;
    wire [2:0] rd;
    wire [2:0] rs;
    wire [7:0] immediate;


    // ============================================================
    // CONTROL UNIT SIGNALS
    // ============================================================

    wire [2:0] alu_op;
    wire [1:0] wb_sel;

    wire reg_write_req;
    wire flag_write_req;

    wire mem_read_req;
    wire mem_write_req;

    wire jump;
    wire jump_zero;

    wire halt_req;


    // ============================================================
    // FSM SIGNALS
    // ============================================================

    wire [2:0] state;

    wire fetch_state;
    wire decode_state;
    wire execute_state;
    wire writeback_state;


    // ============================================================
    // REGISTER FILE SIGNALS
    // ============================================================

    wire [7:0] rd_value;
    wire [7:0] rs_value;

    wire       register_write_enable;

    reg [7:0] writeback_data;


    // ============================================================
    // ALU SIGNALS
    // ============================================================

    wire [7:0] alu_result;

    wire alu_zero;
    wire alu_carry;


    // ============================================================
    // STATUS REGISTER SIGNALS
    // ============================================================

    wire zero_flag;
    wire carry_flag;

    wire flag_write_enable;


    // ============================================================
    // DATA MEMORY SIGNALS
    // ============================================================

    wire [7:0] memory_read_data;

    wire memory_write_enable;


    // ============================================================
    // PROGRAM COUNTER
    // ============================================================

    program_counter u_pc (
        .clk(clk),
        .reset(reset),

        .enable(pc_enable),
        .load(pc_load),
        .next_pc(next_pc),

        .pc(pc)
    );


    // ============================================================
    // INSTRUCTION MEMORY
    // ============================================================

    instruction_memory #(
        .MEM_FILE(PROGRAM_FILE)
    ) u_imem (
        .address(pc),
        .instruction(instruction_from_memory)
    );


    // ============================================================
    // INSTRUCTION REGISTER
    // ============================================================

    instruction_register u_ir (
        .clk(clk),
        .reset(reset),

        .load(fetch_state),

        .instruction_in(instruction_from_memory),
        .instruction_out(current_instruction)
    );


    // ============================================================
    // INSTRUCTION DECODER
    // ============================================================

    instruction_decoder u_decoder (
        .instruction(current_instruction),

        .opcode(opcode),
        .rd(rd),
        .rs(rs),
        .immediate(immediate)
    );


    // ============================================================
    // CONTROL UNIT
    // ============================================================

    control_unit u_control (
        .opcode(opcode),

        .alu_op(alu_op),
        .wb_sel(wb_sel),

        .reg_write_req(reg_write_req),
        .flag_write_req(flag_write_req),

        .mem_read_req(mem_read_req),
        .mem_write_req(mem_write_req),

        .jump(jump),
        .jump_zero(jump_zero),

        .halt(halt_req)
    );


    // ============================================================
    // CONTROL FSM
    // ============================================================

    control_fsm u_fsm (
        .clk(clk),
        .reset(reset),

        .halt_req(halt_req),

        .state(state),

        .fetch_state(fetch_state),
        .decode_state(decode_state),
        .execute_state(execute_state),
        .writeback_state(writeback_state),

        .halted(halted)
    );


    // ============================================================
    // REGISTER FILE
    // ============================================================

    register_file u_regfile (
        .clk(clk),
        .reset(reset),

        // Rd is operand A
        .read_addr1(rd),

        // Rs is operand B
        .read_addr2(rs),

        // Destination register
        .write_addr(rd),

        // Data selected by writeback MUX
        .write_data(writeback_data),

        // Physical register write enable
        .write_enable(register_write_enable),

        .read_data1(rd_value),
        .read_data2(rs_value)
    );


    // ============================================================
    // ALU
    // ============================================================

    alu u_alu (
        .a(rd_value),
        .b(rs_value),

        .op(alu_op),

        .result(alu_result),

        .zero(alu_zero),
        .carry(alu_carry)
    );


    // ============================================================
    // STATUS REGISTER
    // ============================================================

    status_register u_status (
        .clk(clk),
        .reset(reset),

        .write_enable(flag_write_enable),

        .zero_in(alu_zero),
        .carry_in(alu_carry),

        .zero_flag(zero_flag),
        .carry_flag(carry_flag)
    );


    // ============================================================
    // DATA MEMORY
    // ============================================================

    data_memory u_dmem (
        .clk(clk),

        .mem_read(mem_read_req),
        .mem_write(memory_write_enable),

        .address(immediate),

        // STORE Rd,address
        .write_data(rd_value),

        .read_data(memory_read_data)
    );


    // ============================================================
    // WRITEBACK MULTIPLEXER
    // ============================================================

    always @(*) begin

        case (wb_sel)

            // ALU result
            2'b00: begin
                writeback_data = alu_result;
            end


            // Immediate value
            2'b01: begin
                writeback_data = immediate;
            end


            // Data Memory
            2'b10: begin
                writeback_data = memory_read_data;
            end


            // Rs register value
            2'b11: begin
                writeback_data = rs_value;
            end


            default: begin
                writeback_data = 8'b00000000;
            end

        endcase

    end


    // ============================================================
    // REGISTER WRITE CONTROL
    // ============================================================

    // An instruction may request a register write,
    // but the actual write is only allowed during WRITEBACK.

    assign register_write_enable =
        writeback_state &&
        reg_write_req;


    // ============================================================
    // STATUS FLAG WRITE CONTROL
    // ============================================================

    // ADD, SUB, AND, OR, XOR and CMP can request
    // flag updates.
    //
    // The actual flags are captured during EXECUTE.

    assign flag_write_enable =
        execute_state &&
        flag_write_req;


    // ============================================================
    // DATA MEMORY WRITE CONTROL
    // ============================================================

    // STORE writes Data Memory during EXECUTE.

    assign memory_write_enable =
        execute_state &&
        mem_write_req;


    // ============================================================
    // PROGRAM COUNTER CONTROL
    // ============================================================

    // PC changes only once the current instruction
    // reaches WRITEBACK.

    assign pc_enable =
        writeback_state;


    // JMP:
    //     jump = 1
    //
    // JZ:
    //     jump_zero = 1
    //     AND stored Zero Flag = 1

    assign pc_load =
        writeback_state &&
        (
            jump ||
            (jump_zero && zero_flag)
        );


    // JMP/JZ destination comes from
    // instruction bits [7:0].

    assign next_pc =
        immediate;


    // ============================================================
    // DEBUG OUTPUTS
    // ============================================================

    assign pc_debug =
        pc;

    assign instruction_debug =
        current_instruction;

    assign state_debug =
        state;

    assign zero_debug =
        zero_flag;

    assign carry_debug =
        carry_flag;


endmodule

tb/minirisc_assembler_tb.v
`timescale 1ns/1ps

module minirisc_assembler_tb;

    reg clk;
    reg reset;

    wire [7:0]  pc;
    wire [15:0] instruction;
    wire [2:0]  state;

    wire zero;
    wire carry;
    wire halted;


    // ============================================================
    // MINIRISC CPU
    //
    // IMPORTANT:
    // This CPU is now loading the file generated by Python.
    // ============================================================

    minirisc_cpu #(
        .PROGRAM_FILE("programs/assembled_program.mem")
    ) dut (
        .clk(clk),
        .reset(reset),

        .pc_debug(pc),
        .instruction_debug(instruction),
        .state_debug(state),

        .zero_debug(zero),
        .carry_debug(carry),

        .halted(halted)
    );


    // ============================================================
    // CLOCK
    // ============================================================

    initial begin
        clk = 0;
        forever #5 clk = ~clk;
    end


    // ============================================================
    // TEST
    // ============================================================

    initial begin

        $dumpfile("sim/minirisc_assembler.vcd");
        $dumpvars(0, minirisc_assembler_tb);


        // --------------------------------------------------------
        // Reset CPU
        // --------------------------------------------------------

        reset = 1;

        #12;

        reset = 0;


        // --------------------------------------------------------
        // Run assembled program
        // --------------------------------------------------------

        #220;


        $display("");
        $display("==========================================");
        $display("       ASSEMBLER -> CPU TEST");
        $display("==========================================");


        // ========================================================
        // CHECK R1
        //
        // Program:
        //
        // LDI R1,5
        // LDI R2,3
        // ADD R1,R2
        //
        // Therefore R1 should become 8
        // ========================================================

        if (dut.u_regfile.registers[1] == 8'd8)
            $display(
                "PASS: R1 = 8"
            );
        else
            $display(
                "FAIL: R1 should be 8, actual = %d",
                dut.u_regfile.registers[1]
            );


        // ========================================================
        // CHECK R2
        // ========================================================

        if (dut.u_regfile.registers[2] == 8'd3)
            $display(
                "PASS: R2 = 3"
            );
        else
            $display(
                "FAIL: R2 should be 3, actual = %d",
                dut.u_regfile.registers[2]
            );


        // ========================================================
        // CHECK DATA MEMORY
        //
        // STORE R1,10
        //
        // Therefore memory[10] should contain 8
        // ========================================================

        if (dut.u_dmem.memory[10] == 8'd8)
            $display(
                "PASS: Memory[10] = 8"
            );
        else
            $display(
                "FAIL: Memory[10] should be 8, actual = %d",
                dut.u_dmem.memory[10]
            );


        // ========================================================
        // CHECK HALT
        // ========================================================

        if (halted == 1'b1)
            $display(
                "PASS: CPU halted"
            );
        else
            $display(
                "FAIL: CPU should be halted"
            );


        // ========================================================
        // FINAL VALUES
        // ========================================================

        $display("");
        $display("------------------------------------------");

        $display(
            "Final R1       = %d",
            dut.u_regfile.registers[1]
        );

        $display(
            "Final R2       = %d",
            dut.u_regfile.registers[2]
        );

        $display(
            "Final Memory10 = %d",
            dut.u_dmem.memory[10]
        );

        $display(
            "Final PC       = %d",
            pc
        );

        $display(
            "Final Halted   = %b",
            halted
        );

        $display("------------------------------------------");

        $display("");
        $display("==========================================");
        $display("   ASSEMBLER -> CPU TEST COMPLETE");
        $display("==========================================");


        $finish;

    end

endmodule

sim/minirisc_assembler.vcd
$date
	Thu Aug 27 15:51:56 2026
$end
$version
	Icarus Verilog
$end
$timescale
	1ps
$end
$scope module minirisc_assembler_tb $end
$var wire 1 ! zero $end
$var wire 3 " state [2:0] $end
$var wire 8 # pc [7:0] $end
$var wire 16 $ instruction [15:0] $end
$var wire 1 % halted $end
$var wire 1 & carry $end
$var reg 1 ' clk $end
$var reg 1 ( reset $end
$scope module dut $end
$var wire 1 & carry_debug $end
$var wire 1 ' clk $end
$var wire 1 ) flag_write_enable $end
$var wire 16 * instruction_debug [15:0] $end
$var wire 1 + memory_write_enable $end
$var wire 8 , next_pc [7:0] $end
$var wire 8 - pc_debug [7:0] $end
$var wire 1 . pc_enable $end
$var wire 1 / pc_load $end
$var wire 1 0 register_write_enable $end
$var wire 1 ( reset $end
$var wire 3 1 state_debug [2:0] $end
$var wire 1 ! zero_debug $end
$var wire 1 2 zero_flag $end
$var wire 1 3 writeback_state $end
$var wire 2 4 wb_sel [1:0] $end
$var wire 3 5 state [2:0] $end
$var wire 8 6 rs_value [7:0] $end
$var wire 3 7 rs [2:0] $end
$var wire 1 8 reg_write_req $end
$var wire 8 9 rd_value [7:0] $end
$var wire 3 : rd [2:0] $end
$var wire 8 ; pc [7:0] $end
$var wire 4 < opcode [3:0] $end
$var wire 8 = memory_read_data [7:0] $end
$var wire 1 > mem_write_req $end
$var wire 1 ? mem_read_req $end
$var wire 1 @ jump_zero $end
$var wire 1 A jump $end
$var wire 16 B instruction_from_memory [15:0] $end
$var wire 8 C immediate [7:0] $end
$var wire 1 % halted $end
$var wire 1 D halt_req $end
$var wire 1 E flag_write_req $end
$var wire 1 F fetch_state $end
$var wire 1 G execute_state $end
$var wire 1 H decode_state $end
$var wire 16 I current_instruction [15:0] $end
$var wire 1 J carry_flag $end
$var wire 1 K alu_zero $end
$var wire 8 L alu_result [7:0] $end
$var wire 3 M alu_op [2:0] $end
$var wire 1 N alu_carry $end
$var parameter 240 O PROGRAM_FILE $end
$var reg 8 P writeback_data [7:0] $end
$scope module u_alu $end
$var wire 3 Q op [2:0] $end
$var wire 8 R b [7:0] $end
$var wire 8 S a [7:0] $end
$var reg 1 N carry $end
$var reg 8 T result [7:0] $end
$var reg 1 K zero $end
$upscope $end
$scope module u_control $end
$var wire 4 U opcode [3:0] $end
$var reg 3 V alu_op [2:0] $end
$var reg 1 E flag_write_req $end
$var reg 1 D halt $end
$var reg 1 A jump $end
$var reg 1 @ jump_zero $end
$var reg 1 ? mem_read_req $end
$var reg 1 > mem_write_req $end
$var reg 1 8 reg_write_req $end
$var reg 2 W wb_sel [1:0] $end
$upscope $end
$scope module u_decoder $end
$var wire 3 X rs [2:0] $end
$var wire 3 Y rd [2:0] $end
$var wire 4 Z opcode [3:0] $end
$var wire 16 [ instruction [15:0] $end
$var wire 8 \ immediate [7:0] $end
$upscope $end
$scope module u_dmem $end
$var wire 8 ] address [7:0] $end
$var wire 1 ' clk $end
$var wire 1 ? mem_read $end
$var wire 1 + mem_write $end
$var wire 8 ^ write_data [7:0] $end
$var wire 8 _ read_data [7:0] $end
$var integer 32 ` i [31:0] $end
$upscope $end
$scope module u_fsm $end
$var wire 1 ' clk $end
$var wire 1 D halt_req $end
$var wire 1 ( reset $end
$var wire 1 3 writeback_state $end
$var wire 1 % halted $end
$var wire 1 F fetch_state $end
$var wire 1 G execute_state $end
$var wire 1 H decode_state $end
$var parameter 3 a DECODE $end
$var parameter 3 b EXECUTE $end
$var parameter 3 c FETCH $end
$var parameter 3 d HALT $end
$var parameter 3 e WRITEBACK $end
$var reg 3 f next_state [2:0] $end
$var reg 3 g state [2:0] $end
$upscope $end
$scope module u_imem $end
$var wire 16 h instruction [15:0] $end
$var wire 8 i address [7:0] $end
$var parameter 240 j MEM_FILE $end
$var integer 32 k i [31:0] $end
$upscope $end
$scope module u_ir $end
$var wire 1 ' clk $end
$var wire 16 l instruction_in [15:0] $end
$var wire 1 F load $end
$var wire 1 ( reset $end
$var reg 16 m instruction_out [15:0] $end
$upscope $end
$scope module u_pc $end
$var wire 1 ' clk $end
$var wire 1 . enable $end
$var wire 1 / load $end
$var wire 8 n next_pc [7:0] $end
$var wire 1 ( reset $end
$var reg 8 o pc [7:0] $end
$upscope $end
$scope module u_regfile $end
$var wire 1 ' clk $end
$var wire 3 p read_addr1 [2:0] $end
$var wire 3 q read_addr2 [2:0] $end
$var wire 8 r read_data1 [7:0] $end
$var wire 8 s read_data2 [7:0] $end
$var wire 1 ( reset $end
$var wire 3 t write_addr [2:0] $end
$var wire 8 u write_data [7:0] $end
$var wire 1 0 write_enable $end
$var integer 32 v i [31:0] $end
$upscope $end
$scope module u_status $end
$var wire 1 N carry_in $end
$var wire 1 ' clk $end
$var wire 1 ( reset $end
$var wire 1 ) write_enable $end
$var wire 1 K zero_in $end
$var reg 1 J carry_flag $end
$var reg 1 2 zero_flag $end
$upscope $end
$upscope $end
$upscope $end
$enddefinitions $end
$comment Show the parameter values. $end
$dumpall
b11100000111001001101111011001110111001001100001011011010111001100101111011000010111001101110011011001010110110101100010011011000110010101100100010111110111000001110010011011110110011101110010011000010110110100101110011011010110010101101101 j
b11 e
b100 d
b0 c
b10 b
b1 a
b11100000111001001101111011001110111001001100001011011010111001100101111011000010111001101110011011001010110110101100010011011000110010101100100010111110111000001110010011011110110011101110010011000010110110100101110011011010110010101101101 O
$end
#0
$dumpvars
bx v
bx u
bx t
bx s
bx r
bx q
bx p
bx o
bx n
bx m
bx l
b100000000 k
bx i
bx h
bx g
bx f
b100000000 `
bx _
bx ^
bx ]
bx \
bx [
bx Z
bx Y
bx X
bx W
bx V
bx U
bx T
bx S
bx R
bx Q
bx P
xN
bx M
bx L
xK
xJ
bx I
xH
xG
xF
xE
xD
bx C
bx B
xA
x@
x?
x>
bx =
bx <
bx ;
bx :
bx 9
x8
bx 7
bx 6
bx 5
bx 4
x3
x2
bx 1
x0
x/
x.
bx -
bx ,
x+
bx *
x)
1(
0'
x&
x%
bx $
bx #
bx "
x!
$end
#5000
b0 P
b0 u
b0 =
b0 _
1K
b0 L
b0 T
0N
b0 6
b0 R
b0 s
b0 9
b0 S
b0 ^
b0 r
0D
0@
0A
0>
0?
0E
08
b0 4
b0 W
b0 M
b0 Q
b0 V
b1001000000101 B
b1001000000101 h
b1001000000101 l
b0 ,
b0 n
b0 C
b0 \
b0 ]
b0 7
b0 X
b0 q
b0 :
b0 Y
b0 p
b0 t
b0 <
b0 U
b0 Z
b1 f
0+
0)
0/
00
b0 #
b0 -
b0 ;
b0 i
b0 o
b0 $
b0 *
b0 I
b0 [
b0 m
1F
0H
0G
0.
03
0%
b0 "
b0 1
b0 5
b0 g
0&
0J
0!
02
b1000 v
1'
#10000
0'
#12000
0(
#15000
b101 P
b101 u
b1 4
b1 W
18
b10 f
b101 ,
b101 n
b101 C
b101 \
b101 ]
b1 :
b1 Y
b1 p
b1 t
b1 <
b1 U
b1 Z
0F
1H
b1 "
b1 1
b1 5
b1 g
b1001000000101 $
b1001000000101 *
b1001000000101 I
b1001000000101 [
b1001000000101 m
1'
#20000
0'
#25000
b11 f
0H
1G
b10 "
b10 1
b10 5
b10 g
1'
#30000
0'
#35000
b0 f
10
0G
1.
13
b11 "
b11 1
b11 5
b11 g
1'
#40000
0'
#45000
b1010000000011 B
b1010000000011 h
b1010000000011 l
b1 f
00
0K
b101 L
b101 T
b1 #
b1 -
b1 ;
b1 i
b1 o
1F
0.
03
b0 "
b0 1
b0 5
b0 g
b101 9
b101 S
b101 ^
b101 r
1'
#50000
0'
#55000
1K
b0 L
b0 T
b11 P
b11 u
b0 9
b0 S
b0 ^
b0 r
b10 f
b11 ,
b11 n
b11 C
b11 \
b11 ]
b10 :
b10 Y
b10 p
b10 t
0F
1H
b1 "
b1 1
b1 5
b1 g
b1010000000011 $
b1010000000011 *
b1010000000011 I
b1010000000011 [
b1010000000011 m
1'
#60000
0'
#65000
b11 f
0H
1G
b10 "
b10 1
b10 5
b10 g
1'
#70000
0'
#75000
b0 f
10
0G
1.
13
b11 "
b11 1
b11 5
b11 g
1'
#80000
0'
#85000
b11001010000000 B
b11001010000000 h
b11001010000000 l
b1 f
00
0K
b11 L
b11 T
b10 #
b10 -
b10 ;
b10 i
b10 o
1F
0.
03
b0 "
b0 1
b0 5
b0 g
b11 9
b11 S
b11 ^
b11 r
1'
#90000
0'
#95000
b1000 P
b1000 u
b1000 L
b1000 T
b11 6
b11 R
b11 s
b101 9
b101 S
b101 ^
b101 r
1E
18
b0 4
b0 W
b10 f
b10000000 ,
b10000000 n
b10000000 C
b10000000 \
b10000000 ]
b10 7
b10 X
b10 q
b1 :
b1 Y
b1 p
b1 t
b11 <
b11 U
b11 Z
0F
1H
b1 "
b1 1
b1 5
b1 g
b11001010000000 $
b11001010000000 *
b11001010000000 I
b11001010000000 [
b11001010000000 m
1'
#100000
0'
#105000
b11 f
1)
0H
1G
b10 "
b10 1
b10 5
b10 g
1'
#110000
0'
#115000
b0 f
0)
10
0G
1.
13
b11 "
b11 1
b11 5
b11 g
1'
#120000
0'
#125000
b1011 P
b1011 u
b1001001000001010 B
b1001001000001010 h
b1001001000001010 l
b1 f
00
b1011 L
b1011 T
b11 #
b11 -
b11 ;
b11 i
b11 o
1F
0.
03
b0 "
b0 1
b0 5
b0 g
b1000 9
b1000 S
b1000 ^
b1000 r
1'
#130000
0'
#135000
b1000 P
b1000 u
b1000 L
b1000 T
b0 6
b0 R
b0 s
1>
0E
08
b10 f
b1010 ,
b1010 n
b1010 C
b1010 \
b1010 ]
b0 7
b0 X
b0 q
b1001 <
b1001 U
b1001 Z
0F
1H
b1 "
b1 1
b1 5
b1 g
b1001001000001010 $
b1001001000001010 *
b1001001000001010 I
b1001001000001010 [
b1001001000001010 m
1'
#140000
0'
#145000
b11 f
1+
0H
1G
b10 "
b10 1
b10 5
b10 g
1'
#150000
0'
#155000
b0 f
0+
0G
1.
13
b11 "
b11 1
b11 5
b11 g
1'
#160000
0'
#165000
b1111000000000000 B
b1111000000000000 h
b1111000000000000 l
b1 f
b100 #
b100 -
b100 ;
b100 i
b100 o
1F
0.
03
b0 "
b0 1
b0 5
b0 g
1'
#170000
0'
#175000
b0 P
b0 u
1K
b0 L
b0 T
b0 9
b0 S
b0 ^
b0 r
1D
0>
b100 f
b0 ,
b0 n
b0 C
b0 \
b0 ]
b0 :
b0 Y
b0 p
b0 t
b1111 <
b1111 U
b1111 Z
0F
1H
b1 "
b1 1
b1 5
b1 g
b1111000000000000 $
b1111000000000000 *
b1111000000000000 I
b1111000000000000 [
b1111000000000000 m
1'
#180000
0'
#185000
0H
1%
b100 "
b100 1
b100 5
b100 g
1'
