rtl/status_register.v
module status_register (
    input  wire clk,
    input  wire reset,
    input  wire write_enable,

    input  wire zero_in,
    input  wire carry_in,

    output reg  zero_flag,
    output reg  carry_flag
);

    always @(posedge clk) begin

        if (reset) begin
            zero_flag  <= 1'b0;
            carry_flag <= 1'b0;
        end

        else if (write_enable) begin
            zero_flag  <= zero_in;
            carry_flag <= carry_in;
        end

    end

endmodule

tb/status_register_tb.v
`timescale 1ns/1ps

module status_register_tb;

    reg clk;
    reg reset;
    reg write_enable;

    reg zero_in;
    reg carry_in;

    wire zero_flag;
    wire carry_flag;


    status_register dut (
        .clk(clk),
        .reset(reset),
        .write_enable(write_enable),

        .zero_in(zero_in),
        .carry_in(carry_in),

        .zero_flag(zero_flag),
        .carry_flag(carry_flag)
    );


    // Clock generator
    initial begin
        clk = 0;
        forever #5 clk = ~clk;
    end


    initial begin

        $dumpfile("sim/status_register.vcd");
        $dumpvars(0, status_register_tb);

        $display("TIME CLK RESET WE | Z_IN C_IN | Z C");

        $monitor(
            "%4t  %b    %b    %b |   %b    %b  | %b %b",
            $time,
            clk,
            reset,
            write_enable,
            zero_in,
            carry_in,
            zero_flag,
            carry_flag
        );


        // Reset
        reset        = 1;
        write_enable = 0;
        zero_in      = 0;
        carry_in     = 0;

        #10;


        // Release reset
        reset = 0;


        // Prepare Z=1, C=0
        write_enable = 1;
        zero_in      = 1;
        carry_in     = 0;

        #10;


        // Stop writing
        write_enable = 0;


        // Change inputs, but flags should NOT change
        zero_in  = 0;
        carry_in = 1;

        #10;


        // Now allow new flags to be stored
        write_enable = 1;

        #10;


        write_enable = 0;

        #10;


        $finish;

    end

endmodule

sim/status_register.vcd
$date
	Thu Aug 27 13:15:16 2026
$end
$version
	Icarus Verilog
$end
$timescale
	1ps
$end
$scope module status_register_tb $end
$var wire 1 ! zero_flag $end
$var wire 1 " carry_flag $end
$var reg 1 # carry_in $end
$var reg 1 $ clk $end
$var reg 1 % reset $end
$var reg 1 & write_enable $end
$var reg 1 ' zero_in $end
$scope module dut $end
$var wire 1 # carry_in $end
$var wire 1 $ clk $end
$var wire 1 % reset $end
$var wire 1 & write_enable $end
$var wire 1 ' zero_in $end
$var reg 1 " carry_flag $end
$var reg 1 ! zero_flag $end
$upscope $end
$upscope $end
$enddefinitions $end
$comment Show the parameter values. $end
$dumpall
$end
#0
$dumpvars
0'
0&
1%
0$
0#
x"
x!
$end
#5000
0"
0!
1$
#10000
0$
1'
1&
0%
#15000
1!
1$
#20000
0$
1#
0'
0&
#25000
1$
#30000
0$
1&
#35000
1"
0!
1$
#40000
0$
0&
